django_pre_post/__init__.py
django_pre_post/admin.py
django_pre_post/forms.py
django_pre_post/models.py
django_pre_post/settings.py
django_pre_post/urls.py
django_pre_post/util.py
django_pre_post/views.py
django_pre_post/wsgi.py
django_pre_post/migrations/0001_initial.py
django_pre_post/migrations/__init__.py
django_pre_post/templates/base.html
django_pre_post/templates/django_pre_post/fill_in_the_blank.html
django_pre_post/templates/django_pre_post/frameless_questionnaire.html
django_pre_post/templates/django_pre_post/frameless_success.html
django_pre_post/templates/django_pre_post/multiple_choice.html
django_pre_post/templates/django_pre_post/numeric.html
django_pre_post/templates/django_pre_post/open_ended.html
django_pre_post/templates/django_pre_post/questionnaire_form.html
django_pre_post/templates/django_pre_post/rank.html
django_pre_post/templates/django_pre_post/successful_post.html
django_pre_post-1.0.0.dist-info/DESCRIPTION.rst
django_pre_post-1.0.0.dist-info/METADATA
django_pre_post-1.0.0.dist-info/RECORD
django_pre_post-1.0.0.dist-info/WHEEL
django_pre_post-1.0.0.dist-info/dependency_links.txt
django_pre_post-1.0.0.dist-info/metadata.json
django_pre_post-1.0.0.dist-info/top_level.txt
