Metadata-Version: 2.0
Name: django-pre-post
Version: 1.0.0
Summary: This package provides a framework for surveys and questionnaires
Home-page: UNKNOWN
Author: Silly Inventor
Author-email: SillyInventor@gmail.com
License: UNKNOWN
Keywords: test,pre-post,questionnaire,survey
Platform: UNKNOWN
Requires-Dist: Django (==1.10.6)
Requires-Dist: django-bootstrap3 (==8.2.2)
